LICENSE
MANIFEST.in
README.md
setup.cfg
setup.py
superconsole/Console.py
superconsole/__init__.py
superconsole.egg-info/PKG-INFO
superconsole.egg-info/SOURCES.txt
superconsole.egg-info/dependency_links.txt
superconsole.egg-info/requires.txt
superconsole.egg-info/top_level.txt