Metadata-Version: 2.1
Name: superconsole
Version: 0.0.1
Summary: Expanded console for Python
Home-page: https://github.com/Dmunch04/SuperConsole
Author: Munchii
Author-email: contact@munchii.me
License: MIT
Keywords: expanded console for python
Platform: UNKNOWN
Classifier: Development Status :: 4 - Beta
Classifier: Intended Audience :: End Users/Desktop
Classifier: Intended Audience :: Developers
Classifier: License :: OSI Approved :: MIT License
Classifier: Programming Language :: Python :: 2
Classifier: Programming Language :: Python :: 3
Classifier: Operating System :: OS Independent
